{
  "kategories": [
    {
      "nama": "kegiatan",
      "slug": "kegiatan"
    },
    {
      "nama": "pewartaan",
      "slug": "pewartaan"
    },
    {
      "nama": "liturgi",
      "slug": "liturgi"
    }
  ],
  "statics": [
    {
      "judul": "Sejarah",
      "slug": "sejarah",
      "blocks": [
        {
          "__component": "shared.image",
          "file": "coffee-art.jpg"
        },
        {
          "__component": "shared.rich-text-md",
          "body": "paragraphs.1"
        },
        {
          "__component": "shared.image",
          "file": "coffee-beans.jpg"
        },
        {
          "__component": "shared.rich-text-md",
          "body": "paragraphs.4"
        }
      ]
    }
  ],
  "beritas": [
    {
      "judul": "Obviously Failed",
      "deskripsi": "Lorem ipsum dolor sit amet consectetur adipisicing elit. Dolores est voluptate.",
      "blocks": [
        {
          "__component": "shared.image",
          "file": "obviously-failed.png"
        },
        {
          "__component": "shared.rich-text-md",
          "body": "paragraphs.1"
        }
      ]
    },
    {
      "judul": "Obviously Good",
      "blocks": [
        {
          "__component": "shared.image",
          "file": "obviously-good.png"
        },
        {
          "__component": "shared.rich-text-md",
          "body": "paragraphs.1"
        }
      ]
    },
    {
      "judul": "Obviously Randomly",
      "blocks": [
        {
          "__component": "shared.image",
          "file": "obviously-randomly.png"
        },
        {
          "__component": "shared.rich-text-md",
          "body": "paragraphs.1"
        }
      ]
    },
    {
      "judul": "Obviously Confusing",
      "blocks": [
        {
          "__component": "shared.image",
          "file": "obviously-confusing.png"
        },
        {
          "__component": "shared.rich-text-md",
          "body": "paragraphs.1"
        }
      ]
    },
    {
      "judul": "Obviously Peaceful",
      "blocks": [
        {
          "__component": "shared.image",
          "file": "obviously-peaceful.png"
        },
        {
          "__component": "shared.rich-text-md",
          "body": "paragraphs.1"
        }
      ]
    },
    {
      "judul": "Pelantikan Pengurus DPP 2024-2027",
      "slug": "pelantikan-pengurus-dpp-2024-2027",
      "kategori": [{ "id": 1 }],
      "blocks": [
        {
          "__component": "shared.slider",
          "files": ["coffee-art.jpg", "coffee-beans.jpg"]
        },
        {
          "__component": "shared.rich-text-md",
          "body": "paragraphs.1"
        },
        {
          "__component": "shared.image",
          "file": "coffee-art.jpg"
        }
      ]
    }
  ]
}
